half_hour-0.1.1.dist-info/licenses/LICENSE
hh/__init__.py
hh/hha.py
hh/hhd.py
hh/hhl.py
half_hour-0.1.1.dist-info/METADATA
half_hour-0.1.1.dist-info/WHEEL
half_hour-0.1.1.dist-info/entry_points.txt
half_hour-0.1.1.dist-info/top_level.txt
half_hour-0.1.1.dist-info/RECORD
